CMakeLists.txt
LICENSE
MANIFEST.in
README.md
pyproject.toml
setup.py
pylibreoffice/__init__.py
pylibreoffice/core.py
pylibreoffice/py_office.pyx
pylibreoffice.egg-info/PKG-INFO
pylibreoffice.egg-info/SOURCES.txt
pylibreoffice.egg-info/dependency_links.txt
pylibreoffice.egg-info/not-zip-safe
pylibreoffice.egg-info/requires.txt
pylibreoffice.egg-info/top_level.txt
src/main.cxx
src/office.cxx
src/office.hpp
src/py_office.cpp
src/pybind_office.cpp
tests/__init__.py
tests/test_conv.py