Metadata-Version: 2.1
Name: pylibreoffice
Version: 0.1.4
Summary: A Python library for handling Microsoft Office documents, built with LibreOfficeKit.
Home-page: https://github.com/begonia-org/pylibreoffice
Author: vforfreedom
Author-email: vforfreedom <vforfreedom96@gmail.com>
Project-URL: Homepage, https://github.com/begonia-org/pylibreoffice
Project-URL: Issues, https://github.com/begonia-org/pylibreoffice/issues
Project-URL: Documentation, https://github.com/begonia-org/pylibreoffice
Project-URL: Repository, https://github.com/begonia-org/pylibreoffice.git
Keywords: office,libreoffice,doc,ppt,xls,docx,xlsx,pptx,pdf,libreofficekit,cython,pybind11
Platform: Linux
License-File: LICENSE
Requires-Dist: Cython
Requires-Dist: pybind11
